{
  "layer": "layer01_linguistic_expression_extraction",
  "num_expressions": 60,
  "expressions": [
    {
      "expr_id": "expr_00000",
      "text": "\"Each Time You Break My Heart\"",
      "label": "song",
      "justification": "Title of the song.",
      "evidence": [
        {
          "chunk_id": "chunk_0000",
          "chunk_start_char": -1,
          "chunk_end_char": -1,
          "doc_start_char": -1,
          "doc_end_char": -1,
          "snippet": "\" Each Time You Break My Heart \" is a song recorded by British singer Nick Kamen , for his eponymous debut studio album ( 1987 ) . It was released by Sire Records on 2 November 1986 as his debut single in 7-inch and 12-inch maxi formats . Kamen had gained popularity by starring in a 1985 Levi 's tel"
        }
      ]
    },
    {
      "expr_id": "expr_00001",
      "text": "Nick Kamen",
      "label": "person",
      "justification": "British singer who recorded the song.",
      "evidence": [
        {
          "chunk_id": "chunk_0000",
          "chunk_start_char": 70,
          "chunk_end_char": 80,
          "doc_start_char": 70,
          "doc_end_char": 80,
          "snippet": "\" Each Time You Break My Heart \" is a song recorded by British singer Nick Kamen , for his eponymous debut studio album ( 1987 ) . It was released by Sire Recor"
        }
      ]
    },
    {
      "expr_id": "expr_00002",
      "text": "Sire Records",
      "label": "record label",
      "justification": "Label that released the single.",
      "evidence": [
        {
          "chunk_id": "chunk_0000",
          "chunk_start_char": 150,
          "chunk_end_char": 162,
          "doc_start_char": 150,
          "doc_end_char": 162,
          "snippet": "Nick Kamen , for his eponymous debut studio album ( 1987 ) . It was released by Sire Records on 2 November 1986 as his debut single in 7-inch and 12-inch maxi formats . Kam"
        }
      ]
    },
    {
      "expr_id": "expr_00003",
      "text": "2 November 1986",
      "label": "date",
      "justification": "Release date of the single.",
      "evidence": [
        {
          "chunk_id": "chunk_0000",
          "chunk_start_char": 166,
          "chunk_end_char": 181,
          "doc_start_char": 166,
          "doc_end_char": 181,
          "snippet": "his eponymous debut studio album ( 1987 ) . It was released by Sire Records on 2 November 1986 as his debut single in 7-inch and 12-inch maxi formats . Kamen had gained popul"
        }
      ]
    },
    {
      "expr_id": "expr_00004",
      "text": "Levi's television commercial",
      "label": "commercial",
      "justification": "Commercial that boosted Kamen's popularity.",
      "evidence": [
        {
          "chunk_id": "chunk_0000",
          "chunk_start_char": -1,
          "chunk_end_char": -1,
          "doc_start_char": -1,
          "doc_end_char": -1,
          "snippet": "\" Each Time You Break My Heart \" is a song recorded by British singer Nick Kamen , for his eponymous debut studio album ( 1987 ) . It was released by Sire Records on 2 November 1986 as his debut single in 7-inch and 12-inch maxi formats . Kamen had gained popularity by starring in a 1985 Levi 's tel"
        }
      ]
    },
    {
      "expr_id": "expr_00005",
      "text": "Madonna",
      "label": "person",
      "justification": "Writer and producer of the song.",
      "evidence": [
        {
          "chunk_id": "chunk_0000",
          "chunk_start_char": 496,
          "chunk_end_char": 503,
          "doc_start_char": 496,
          "doc_end_char": 503,
          "snippet": "u Break My Heart \" was the lead single from his album , written and produced by Madonna and Stephen Bray . It was originally set to be included on Madonna 's third stu"
        }
      ]
    },
    {
      "expr_id": "expr_00006",
      "text": "Stephen Bray",
      "label": "person",
      "justification": "Co‑writer and co‑producer of the song.",
      "evidence": [
        {
          "chunk_id": "chunk_0000",
          "chunk_start_char": 508,
          "chunk_end_char": 520,
          "doc_start_char": 508,
          "doc_end_char": 520,
          "snippet": "eart \" was the lead single from his album , written and produced by Madonna and Stephen Bray . It was originally set to be included on Madonna 's third studio album , True"
        }
      ]
    },
    {
      "expr_id": "expr_00007",
      "text": "True Blue",
      "label": "album",
      "justification": "Madonna's album that originally intended to include the song.",
      "evidence": [
        {
          "chunk_id": "chunk_0000",
          "chunk_start_char": 595,
          "chunk_end_char": 604,
          "doc_start_char": 595,
          "doc_end_char": 604,
          "snippet": "Bray . It was originally set to be included on Madonna 's third studio album , True Blue ( 1986 ) , but failed to make the final track list . Madonna also provided back"
        }
      ]
    },
    {
      "expr_id": "expr_00008",
      "text": "Bee Gees",
      "label": "band",
      "justification": "Group referenced in a comparison.",
      "evidence": [
        {
          "chunk_id": "chunk_0000",
          "chunk_start_char": 932,
          "chunk_end_char": 940,
          "doc_start_char": 932,
          "doc_end_char": 940,
          "snippet": "ne 's \" New and Noteworthy \" single list , receiving comparison to songs by the Bee Gees . It was a commercial success , reaching the top ten of the record charts in Fr"
        }
      ]
    },
    {
      "expr_id": "expr_00009",
      "text": "Billboard magazine",
      "label": "magazine",
      "justification": "Publication that featured the song.",
      "evidence": [
        {
          "chunk_id": "chunk_0000",
          "chunk_start_char": 836,
          "chunk_end_char": 854,
          "doc_start_char": 836,
          "doc_end_char": 854,
          "snippet": "was directed by Jean - Baptiste Mondino . The synth - pop song was featured in Billboard magazine 's \" New and Noteworthy \" single list , receiving comparison to songs by the Be"
        }
      ]
    },
    {
      "expr_id": "expr_00010",
      "text": "New and Noteworthy single list",
      "label": "list",
      "justification": "Billboard list where the song appeared.",
      "evidence": [
        {
          "chunk_id": "chunk_0000",
          "chunk_start_char": -1,
          "chunk_end_char": -1,
          "doc_start_char": -1,
          "doc_end_char": -1,
          "snippet": "\" Each Time You Break My Heart \" is a song recorded by British singer Nick Kamen , for his eponymous debut studio album ( 1987 ) . It was released by Sire Records on 2 November 1986 as his debut single in 7-inch and 12-inch maxi formats . Kamen had gained popularity by starring in a 1985 Levi 's tel"
        }
      ]
    },
    {
      "expr_id": "expr_00011",
      "text": "France",
      "label": "country",
      "justification": "Country where the song charted.",
      "evidence": [
        {
          "chunk_id": "chunk_0000",
          "chunk_start_char": 1018,
          "chunk_end_char": 1024,
          "doc_start_char": 1018,
          "doc_end_char": 1024,
          "snippet": "es . It was a commercial success , reaching the top ten of the record charts in France , Germany , Ireland , Italy , Netherlands , Sweden , Switzerland and the United"
        }
      ]
    },
    {
      "expr_id": "expr_00012",
      "text": "Germany",
      "label": "country",
      "justification": "Country where the song charted.",
      "evidence": [
        {
          "chunk_id": "chunk_0000",
          "chunk_start_char": 1027,
          "chunk_end_char": 1034,
          "doc_start_char": 1027,
          "doc_end_char": 1034,
          "snippet": "as a commercial success , reaching the top ten of the record charts in France , Germany , Ireland , Italy , Netherlands , Sweden , Switzerland and the United Kingdom ."
        }
      ]
    },
    {
      "expr_id": "expr_00013",
      "text": "Ireland",
      "label": "country",
      "justification": "Country where the song charted.",
      "evidence": [
        {
          "chunk_id": "chunk_0000",
          "chunk_start_char": 1037,
          "chunk_end_char": 1044,
          "doc_start_char": 1037,
          "doc_end_char": 1044,
          "snippet": "rcial success , reaching the top ten of the record charts in France , Germany , Ireland , Italy , Netherlands , Sweden , Switzerland and the United Kingdom . It attain"
        }
      ]
    },
    {
      "expr_id": "expr_00014",
      "text": "Italy",
      "label": "country",
      "justification": "Country where the song charted.",
      "evidence": [
        {
          "chunk_id": "chunk_0000",
          "chunk_start_char": 1047,
          "chunk_end_char": 1052,
          "doc_start_char": 1047,
          "doc_end_char": 1052,
          "snippet": "ess , reaching the top ten of the record charts in France , Germany , Ireland , Italy , Netherlands , Sweden , Switzerland and the United Kingdom . It attained Silve"
        }
      ]
    },
    {
      "expr_id": "expr_00015",
      "text": "Netherlands",
      "label": "country",
      "justification": "Country where the song charted.",
      "evidence": [
        {
          "chunk_id": "chunk_0000",
          "chunk_start_char": 1055,
          "chunk_end_char": 1066,
          "doc_start_char": 1055,
          "doc_end_char": 1066,
          "snippet": "aching the top ten of the record charts in France , Germany , Ireland , Italy , Netherlands , Sweden , Switzerland and the United Kingdom . It attained Silver certificatio"
        }
      ]
    },
    {
      "expr_id": "expr_00016",
      "text": "Sweden",
      "label": "country",
      "justification": "Country where the song charted.",
      "evidence": [
        {
          "chunk_id": "chunk_0000",
          "chunk_start_char": 1069,
          "chunk_end_char": 1075,
          "doc_start_char": 1069,
          "doc_end_char": 1075,
          "snippet": "ten of the record charts in France , Germany , Ireland , Italy , Netherlands , Sweden , Switzerland and the United Kingdom . It attained Silver certification in Fran"
        }
      ]
    },
    {
      "expr_id": "expr_00017",
      "text": "Switzerland",
      "label": "country",
      "justification": "Country where the song charted.",
      "evidence": [
        {
          "chunk_id": "chunk_0000",
          "chunk_start_char": 1078,
          "chunk_end_char": 1089,
          "doc_start_char": 1078,
          "doc_end_char": 1089,
          "snippet": "he record charts in France , Germany , Ireland , Italy , Netherlands , Sweden , Switzerland and the United Kingdom . It attained Silver certification in France and the Uni"
        }
      ]
    },
    {
      "expr_id": "expr_00018",
      "text": "United Kingdom",
      "label": "country",
      "justification": "Country where the song charted.",
      "evidence": [
        {
          "chunk_id": "chunk_0000",
          "chunk_start_char": 1098,
          "chunk_end_char": 1112,
          "doc_start_char": 1098,
          "doc_end_char": 1112,
          "snippet": "France , Germany , Ireland , Italy , Netherlands , Sweden , Switzerland and the United Kingdom . It attained Silver certification in France and the United Kingdom , and a rem"
        }
      ]
    },
    {
      "expr_id": "expr_00019",
      "text": "United States",
      "label": "country",
      "justification": "Country where the remix became a hit.",
      "evidence": [
        {
          "chunk_id": "chunk_0000",
          "chunk_start_char": 1234,
          "chunk_end_char": 1247,
          "doc_start_char": 1234,
          "doc_end_char": 1247,
          "snippet": "nce and the United Kingdom , and a remix of the track became a dance hit in the United States ."
        }
      ]
    },
    {
      "expr_id": "expr_00020",
      "text": "Jean-Baptiste Mondino",
      "label": "person",
      "justification": "Director of the promotional video.",
      "evidence": [
        {
          "chunk_id": "chunk_0000",
          "chunk_start_char": -1,
          "chunk_end_char": -1,
          "doc_start_char": -1,
          "doc_end_char": -1,
          "snippet": "\" Each Time You Break My Heart \" is a song recorded by British singer Nick Kamen , for his eponymous debut studio album ( 1987 ) . It was released by Sire Records on 2 November 1986 as his debut single in 7-inch and 12-inch maxi formats . Kamen had gained popularity by starring in a 1985 Levi 's tel"
        }
      ]
    },
    {
      "expr_id": "expr_00021",
      "text": "British singer",
      "label": "attribute",
      "justification": "Describes Nick Kamen.",
      "evidence": [
        {
          "chunk_id": "chunk_0000",
          "chunk_start_char": 55,
          "chunk_end_char": 69,
          "doc_start_char": 55,
          "doc_end_char": 69,
          "snippet": "\" Each Time You Break My Heart \" is a song recorded by British singer Nick Kamen , for his eponymous debut studio album ( 1987 ) . It was released by"
        }
      ]
    },
    {
      "expr_id": "expr_00022",
      "text": "eponymous debut studio album",
      "label": "attribute",
      "justification": "Describes the album the song was recorded for.",
      "evidence": [
        {
          "chunk_id": "chunk_0000",
          "chunk_start_char": 91,
          "chunk_end_char": 119,
          "doc_start_char": 91,
          "doc_end_char": 119,
          "snippet": "You Break My Heart \" is a song recorded by British singer Nick Kamen , for his eponymous debut studio album ( 1987 ) . It was released by Sire Records on 2 November 1986 as his debut sing"
        }
      ]
    },
    {
      "expr_id": "expr_00023",
      "text": "7-inch and 12-inch maxi formats",
      "label": "attribute",
      "justification": "Formats in which the single was released.",
      "evidence": [
        {
          "chunk_id": "chunk_0000",
          "chunk_start_char": 205,
          "chunk_end_char": 236,
          "doc_start_char": 205,
          "doc_end_char": 236,
          "snippet": "7 ) . It was released by Sire Records on 2 November 1986 as his debut single in 7-inch and 12-inch maxi formats . Kamen had gained popularity by starring in a 1985 Levi 's television commerci"
        }
      ]
    },
    {
      "expr_id": "expr_00024",
      "text": "lead single",
      "label": "attribute",
      "justification": "Position of the song on the album.",
      "evidence": [
        {
          "chunk_id": "chunk_0000",
          "chunk_start_char": 443,
          "chunk_end_char": 454,
          "doc_start_char": 443,
          "doc_end_char": 454,
          "snippet": "s and signed a record deal with Sire . \" Each Time You Break My Heart \" was the lead single from his album , written and produced by Madonna and Stephen Bray . It was orig"
        }
      ]
    },
    {
      "expr_id": "expr_00025",
      "text": "synth-pop song",
      "label": "genre",
      "justification": "Musical genre of the track.",
      "evidence": [
        {
          "chunk_id": "chunk_0000",
          "chunk_start_char": -1,
          "chunk_end_char": -1,
          "doc_start_char": -1,
          "doc_end_char": -1,
          "snippet": "\" Each Time You Break My Heart \" is a song recorded by British singer Nick Kamen , for his eponymous debut studio album ( 1987 ) . It was released by Sire Records on 2 November 1986 as his debut single in 7-inch and 12-inch maxi formats . Kamen had gained popularity by starring in a 1985 Levi 's tel"
        }
      ]
    },
    {
      "expr_id": "expr_00026",
      "text": "record charts",
      "label": "attribute",
      "justification": "Charts where the song appeared.",
      "evidence": [
        {
          "chunk_id": "chunk_0000",
          "chunk_start_char": 1001,
          "chunk_end_char": 1014,
          "doc_start_char": 1001,
          "doc_end_char": 1014,
          "snippet": "ngs by the Bee Gees . It was a commercial success , reaching the top ten of the record charts in France , Germany , Ireland , Italy , Netherlands , Sweden , Switzerland and"
        }
      ]
    },
    {
      "expr_id": "expr_00027",
      "text": "Silver certification",
      "label": "award",
      "justification": "Certification received in France and the UK.",
      "evidence": [
        {
          "chunk_id": "chunk_0000",
          "chunk_start_char": 1127,
          "chunk_end_char": 1147,
          "doc_start_char": 1127,
          "doc_end_char": 1147,
          "snippet": "Italy , Netherlands , Sweden , Switzerland and the United Kingdom . It attained Silver certification in France and the United Kingdom , and a remix of the track became a dance hit"
        }
      ]
    },
    {
      "expr_id": "expr_00028",
      "text": "remix",
      "label": "version",
      "justification": "Remixed version that became a dance hit.",
      "evidence": [
        {
          "chunk_id": "chunk_0000",
          "chunk_start_char": 1189,
          "chunk_end_char": 1194,
          "doc_start_char": 1189,
          "doc_end_char": 1194,
          "snippet": "dom . It attained Silver certification in France and the United Kingdom , and a remix of the track became a dance hit in the United States ."
        }
      ]
    },
    {
      "expr_id": "expr_00029",
      "text": "song recorded",
      "label": "event",
      "justification": "Action of recording the track.",
      "evidence": [
        {
          "chunk_id": "chunk_0000",
          "chunk_start_char": 38,
          "chunk_end_char": 51,
          "doc_start_char": 38,
          "doc_end_char": 51,
          "snippet": "\" Each Time You Break My Heart \" is a song recorded by British singer Nick Kamen , for his eponymous debut studio album ( 1987 ) ."
        }
      ]
    },
    {
      "expr_id": "expr_00030",
      "text": "released",
      "label": "event",
      "justification": "Action of releasing the single.",
      "evidence": [
        {
          "chunk_id": "chunk_0000",
          "chunk_start_char": 138,
          "chunk_end_char": 146,
          "doc_start_char": 138,
          "doc_end_char": 146,
          "snippet": "tish singer Nick Kamen , for his eponymous debut studio album ( 1987 ) . It was released by Sire Records on 2 November 1986 as his debut single in 7-inch and 12-inch ma"
        }
      ]
    },
    {
      "expr_id": "expr_00031",
      "text": "starring in a commercial",
      "label": "event",
      "justification": "Kamen's appearance that increased his popularity.",
      "evidence": [
        {
          "chunk_id": "chunk_0000",
          "chunk_start_char": -1,
          "chunk_end_char": -1,
          "doc_start_char": -1,
          "doc_end_char": -1,
          "snippet": "\" Each Time You Break My Heart \" is a song recorded by British singer Nick Kamen , for his eponymous debut studio album ( 1987 ) . It was released by Sire Records on 2 November 1986 as his debut single in 7-inch and 12-inch maxi formats . Kamen had gained popularity by starring in a 1985 Levi 's tel"
        }
      ]
    },
    {
      "expr_id": "expr_00032",
      "text": "signed a record deal",
      "label": "event",
      "justification": "Kamen's contract with Sire.",
      "evidence": [
        {
          "chunk_id": "chunk_0000",
          "chunk_start_char": 369,
          "chunk_end_char": 389,
          "doc_start_char": 369,
          "doc_end_char": 389,
          "snippet": "Levi 's television commercial , later deciding to delve into music business and signed a record deal with Sire . \" Each Time You Break My Heart \" was the lead single from his album"
        }
      ]
    },
    {
      "expr_id": "expr_00033",
      "text": "written and produced",
      "label": "event",
      "justification": "Creation of the song by Madonna and Stephen Bray.",
      "evidence": [
        {
          "chunk_id": "chunk_0000",
          "chunk_start_char": 472,
          "chunk_end_char": 492,
          "doc_start_char": 472,
          "doc_end_char": 492,
          "snippet": "th Sire . \" Each Time You Break My Heart \" was the lead single from his album , written and produced by Madonna and Stephen Bray . It was originally set to be included on Madonna '"
        }
      ]
    },
    {
      "expr_id": "expr_00034",
      "text": "included on album",
      "label": "event",
      "justification": "Song's intended inclusion on True Blue.",
      "evidence": [
        {
          "chunk_id": "chunk_0000",
          "chunk_start_char": -1,
          "chunk_end_char": -1,
          "doc_start_char": -1,
          "doc_end_char": -1,
          "snippet": "\" Each Time You Break My Heart \" is a song recorded by British singer Nick Kamen , for his eponymous debut studio album ( 1987 ) . It was released by Sire Records on 2 November 1986 as his debut single in 7-inch and 12-inch maxi formats . Kamen had gained popularity by starring in a 1985 Levi 's tel"
        }
      ]
    },
    {
      "expr_id": "expr_00035",
      "text": "failed to make track list",
      "label": "event",
      "justification": "Song was omitted from True Blue.",
      "evidence": [
        {
          "chunk_id": "chunk_0000",
          "chunk_start_char": -1,
          "chunk_end_char": -1,
          "doc_start_char": -1,
          "doc_end_char": -1,
          "snippet": "\" Each Time You Break My Heart \" is a song recorded by British singer Nick Kamen , for his eponymous debut studio album ( 1987 ) . It was released by Sire Records on 2 November 1986 as his debut single in 7-inch and 12-inch maxi formats . Kamen had gained popularity by starring in a 1985 Levi 's tel"
        }
      ]
    },
    {
      "expr_id": "expr_00036",
      "text": "provided background vocals",
      "label": "event",
      "justification": "Madonna's contribution to the track.",
      "evidence": [
        {
          "chunk_id": "chunk_0000",
          "chunk_start_char": 671,
          "chunk_end_char": 697,
          "doc_start_char": 671,
          "doc_end_char": 697,
          "snippet": "m , True Blue ( 1986 ) , but failed to make the final track list . Madonna also provided background vocals on the track . A promotional video to accompany the single was directed by Jean"
        }
      ]
    },
    {
      "expr_id": "expr_00037",
      "text": "directed promotional video",
      "label": "event",
      "justification": "Video directed by Jean‑Baptiste Mondino.",
      "evidence": [
        {
          "chunk_id": "chunk_0000",
          "chunk_start_char": -1,
          "chunk_end_char": -1,
          "doc_start_char": -1,
          "doc_end_char": -1,
          "snippet": "\" Each Time You Break My Heart \" is a song recorded by British singer Nick Kamen , for his eponymous debut studio album ( 1987 ) . It was released by Sire Records on 2 November 1986 as his debut single in 7-inch and 12-inch maxi formats . Kamen had gained popularity by starring in a 1985 Levi 's tel"
        }
      ]
    },
    {
      "expr_id": "expr_00038",
      "text": "featured in magazine list",
      "label": "event",
      "justification": "Song's appearance on Billboard's list.",
      "evidence": [
        {
          "chunk_id": "chunk_0000",
          "chunk_start_char": -1,
          "chunk_end_char": -1,
          "doc_start_char": -1,
          "doc_end_char": -1,
          "snippet": "\" Each Time You Break My Heart \" is a song recorded by British singer Nick Kamen , for his eponymous debut studio album ( 1987 ) . It was released by Sire Records on 2 November 1986 as his debut single in 7-inch and 12-inch maxi formats . Kamen had gained popularity by starring in a 1985 Levi 's tel"
        }
      ]
    },
    {
      "expr_id": "expr_00039",
      "text": "reaching top ten",
      "label": "state",
      "justification": "Chart performance in multiple countries.",
      "evidence": [
        {
          "chunk_id": "chunk_0000",
          "chunk_start_char": -1,
          "chunk_end_char": -1,
          "doc_start_char": -1,
          "doc_end_char": -1,
          "snippet": "\" Each Time You Break My Heart \" is a song recorded by British singer Nick Kamen , for his eponymous debut studio album ( 1987 ) . It was released by Sire Records on 2 November 1986 as his debut single in 7-inch and 12-inch maxi formats . Kamen had gained popularity by starring in a 1985 Levi 's tel"
        }
      ]
    },
    {
      "expr_id": "expr_00040",
      "text": "attained certification",
      "label": "state",
      "justification": "Silver certification in France and the UK.",
      "evidence": [
        {
          "chunk_id": "chunk_0000",
          "chunk_start_char": -1,
          "chunk_end_char": -1,
          "doc_start_char": -1,
          "doc_end_char": -1,
          "snippet": "\" Each Time You Break My Heart \" is a song recorded by British singer Nick Kamen , for his eponymous debut studio album ( 1987 ) . It was released by Sire Records on 2 November 1986 as his debut single in 7-inch and 12-inch maxi formats . Kamen had gained popularity by starring in a 1985 Levi 's tel"
        }
      ]
    },
    {
      "expr_id": "expr_00041",
      "text": "remix became hit",
      "label": "state",
      "justification": "Remixed version's success in the US.",
      "evidence": [
        {
          "chunk_id": "chunk_0000",
          "chunk_start_char": -1,
          "chunk_end_char": -1,
          "doc_start_char": -1,
          "doc_end_char": -1,
          "snippet": "\" Each Time You Break My Heart \" is a song recorded by British singer Nick Kamen , for his eponymous debut studio album ( 1987 ) . It was released by Sire Records on 2 November 1986 as his debut single in 7-inch and 12-inch maxi formats . Kamen had gained popularity by starring in a 1985 Levi 's tel"
        }
      ]
    },
    {
      "expr_id": "expr_00042",
      "text": "is a song recorded by",
      "label": "relation-bearing expression",
      "justification": "Links the song to Nick Kamen.",
      "evidence": [
        {
          "chunk_id": "chunk_0000",
          "chunk_start_char": 33,
          "chunk_end_char": 54,
          "doc_start_char": 33,
          "doc_end_char": 54,
          "snippet": "\" Each Time You Break My Heart \" is a song recorded by British singer Nick Kamen , for his eponymous debut studio album ( 1987 ) . It"
        }
      ]
    },
    {
      "expr_id": "expr_00043",
      "text": "for his eponymous debut studio album",
      "label": "relation-bearing expression",
      "justification": "Describes the album the song was recorded for.",
      "evidence": [
        {
          "chunk_id": "chunk_0000",
          "chunk_start_char": 83,
          "chunk_end_char": 119,
          "doc_start_char": 83,
          "doc_end_char": 119,
          "snippet": "ach Time You Break My Heart \" is a song recorded by British singer Nick Kamen , for his eponymous debut studio album ( 1987 ) . It was released by Sire Records on 2 November 1986 as his debut sing"
        }
      ]
    },
    {
      "expr_id": "expr_00044",
      "text": "released by",
      "label": "relation-bearing expression",
      "justification": "Links the release to Sire Records.",
      "evidence": [
        {
          "chunk_id": "chunk_0000",
          "chunk_start_char": 138,
          "chunk_end_char": 149,
          "doc_start_char": 138,
          "doc_end_char": 149,
          "snippet": "tish singer Nick Kamen , for his eponymous debut studio album ( 1987 ) . It was released by Sire Records on 2 November 1986 as his debut single in 7-inch and 12-inch maxi"
        }
      ]
    },
    {
      "expr_id": "expr_00045",
      "text": "on 2 November 1986",
      "label": "relation-bearing expression",
      "justification": "Specifies the release date.",
      "evidence": [
        {
          "chunk_id": "chunk_0000",
          "chunk_start_char": 163,
          "chunk_end_char": 181,
          "doc_start_char": 163,
          "doc_end_char": 181,
          "snippet": "for his eponymous debut studio album ( 1987 ) . It was released by Sire Records on 2 November 1986 as his debut single in 7-inch and 12-inch maxi formats . Kamen had gained popul"
        }
      ]
    },
    {
      "expr_id": "expr_00046",
      "text": "as his debut single in 7-inch and 12-inch maxi formats",
      "label": "relation-bearing expression",
      "justification": "Describes the formats of the release.",
      "evidence": [
        {
          "chunk_id": "chunk_0000",
          "chunk_start_char": 182,
          "chunk_end_char": 236,
          "doc_start_char": 182,
          "doc_end_char": 236,
          "snippet": "ebut studio album ( 1987 ) . It was released by Sire Records on 2 November 1986 as his debut single in 7-inch and 12-inch maxi formats . Kamen had gained popularity by starring in a 1985 Levi 's television commerci"
        }
      ]
    },
    {
      "expr_id": "expr_00047",
      "text": "by starring in a 1985 Levi's television commercial",
      "label": "relation-bearing expression",
      "justification": "Explains how Kamen gained popularity.",
      "evidence": [
        {
          "chunk_id": "chunk_0000",
          "chunk_start_char": -1,
          "chunk_end_char": -1,
          "doc_start_char": -1,
          "doc_end_char": -1,
          "snippet": "\" Each Time You Break My Heart \" is a song recorded by British singer Nick Kamen , for his eponymous debut studio album ( 1987 ) . It was released by Sire Records on 2 November 1986 as his debut single in 7-inch and 12-inch maxi formats . Kamen had gained popularity by starring in a 1985 Levi 's tel"
        }
      ]
    },
    {
      "expr_id": "expr_00048",
      "text": "signed a record deal with Sire",
      "label": "relation-bearing expression",
      "justification": "Describes Kamen's contract.",
      "evidence": [
        {
          "chunk_id": "chunk_0000",
          "chunk_start_char": 369,
          "chunk_end_char": 399,
          "doc_start_char": 369,
          "doc_end_char": 399,
          "snippet": "Levi 's television commercial , later deciding to delve into music business and signed a record deal with Sire . \" Each Time You Break My Heart \" was the lead single from his album , written"
        }
      ]
    },
    {
      "expr_id": "expr_00049",
      "text": "was the lead single from his album",
      "label": "relation-bearing expression",
      "justification": "Indicates the song's position on the album.",
      "evidence": [
        {
          "chunk_id": "chunk_0000",
          "chunk_start_char": 435,
          "chunk_end_char": 469,
          "doc_start_char": 435,
          "doc_end_char": 469,
          "snippet": "business and signed a record deal with Sire . \" Each Time You Break My Heart \" was the lead single from his album , written and produced by Madonna and Stephen Bray . It was originally set to b"
        }
      ]
    },
    {
      "expr_id": "expr_00050",
      "text": "written and produced by",
      "label": "relation-bearing expression",
      "justification": "Links the song to Madonna and Stephen Bray.",
      "evidence": [
        {
          "chunk_id": "chunk_0000",
          "chunk_start_char": 472,
          "chunk_end_char": 495,
          "doc_start_char": 472,
          "doc_end_char": 495,
          "snippet": "th Sire . \" Each Time You Break My Heart \" was the lead single from his album , written and produced by Madonna and Stephen Bray . It was originally set to be included on Madonna 's t"
        }
      ]
    },
    {
      "expr_id": "expr_00051",
      "text": "originally set to be included on",
      "label": "relation-bearing expression",
      "justification": "Describes the song's intended placement on True Blue.",
      "evidence": [
        {
          "chunk_id": "chunk_0000",
          "chunk_start_char": 530,
          "chunk_end_char": 562,
          "doc_start_char": 530,
          "doc_end_char": 562,
          "snippet": "ngle from his album , written and produced by Madonna and Stephen Bray . It was originally set to be included on Madonna 's third studio album , True Blue ( 1986 ) , but failed to make the fin"
        }
      ]
    },
    {
      "expr_id": "expr_00052",
      "text": "failed to make the final track list",
      "label": "relation-bearing expression",
      "justification": "Explains why the song was omitted from True Blue.",
      "evidence": [
        {
          "chunk_id": "chunk_0000",
          "chunk_start_char": 620,
          "chunk_end_char": 655,
          "doc_start_char": 620,
          "doc_end_char": 655,
          "snippet": "set to be included on Madonna 's third studio album , True Blue ( 1986 ) , but failed to make the final track list . Madonna also provided background vocals on the track . A promotional video to"
        }
      ]
    },
    {
      "expr_id": "expr_00053",
      "text": "also provided background vocals on the track",
      "label": "relation-bearing expression",
      "justification": "Describes Madonna's contribution.",
      "evidence": [
        {
          "chunk_id": "chunk_0000",
          "chunk_start_char": 666,
          "chunk_end_char": 710,
          "doc_start_char": 666,
          "doc_end_char": 710,
          "snippet": "album , True Blue ( 1986 ) , but failed to make the final track list . Madonna also provided background vocals on the track . A promotional video to accompany the single was directed by Jean - Baptiste M"
        }
      ]
    },
    {
      "expr_id": "expr_00054",
      "text": "was directed by",
      "label": "relation-bearing expression",
      "justification": "Links the promotional video to Jean‑Baptiste Mondino.",
      "evidence": [
        {
          "chunk_id": "chunk_0000",
          "chunk_start_char": 757,
          "chunk_end_char": 772,
          "doc_start_char": 757,
          "doc_end_char": 772,
          "snippet": "ed background vocals on the track . A promotional video to accompany the single was directed by Jean - Baptiste Mondino . The synth - pop song was featured in Billboard magazi"
        }
      ]
    },
    {
      "expr_id": "expr_00055",
      "text": "was featured in",
      "label": "relation-bearing expression",
      "justification": "Links the song to Billboard's list.",
      "evidence": [
        {
          "chunk_id": "chunk_0000",
          "chunk_start_char": 820,
          "chunk_end_char": 835,
          "doc_start_char": 820,
          "doc_end_char": 835,
          "snippet": "mpany the single was directed by Jean - Baptiste Mondino . The synth - pop song was featured in Billboard magazine 's \" New and Noteworthy \" single list , receiving comparison"
        }
      ]
    },
    {
      "expr_id": "expr_00056",
      "text": "receiving comparison to",
      "label": "relation-bearing expression",
      "justification": "Describes the comparison to Bee Gees.",
      "evidence": [
        {
          "chunk_id": "chunk_0000",
          "chunk_start_char": 895,
          "chunk_end_char": 918,
          "doc_start_char": 895,
          "doc_end_char": 918,
          "snippet": "song was featured in Billboard magazine 's \" New and Noteworthy \" single list , receiving comparison to songs by the Bee Gees . It was a commercial success , reaching the top ten of t"
        }
      ]
    },
    {
      "expr_id": "expr_00057",
      "text": "reaching the top ten of the record charts in",
      "label": "relation-bearing expression",
      "justification": "Describes chart performance in multiple countries.",
      "evidence": [
        {
          "chunk_id": "chunk_0000",
          "chunk_start_char": 973,
          "chunk_end_char": 1017,
          "doc_start_char": 973,
          "doc_end_char": 1017,
          "snippet": ", receiving comparison to songs by the Bee Gees . It was a commercial success , reaching the top ten of the record charts in France , Germany , Ireland , Italy , Netherlands , Sweden , Switzerland and the"
        }
      ]
    },
    {
      "expr_id": "expr_00058",
      "text": "attained Silver certification in",
      "label": "relation-bearing expression",
      "justification": "Links certification to France and the UK.",
      "evidence": [
        {
          "chunk_id": "chunk_0000",
          "chunk_start_char": 1118,
          "chunk_end_char": 1150,
          "doc_start_char": 1118,
          "doc_end_char": 1150,
          "snippet": "reland , Italy , Netherlands , Sweden , Switzerland and the United Kingdom . It attained Silver certification in France and the United Kingdom , and a remix of the track became a dance hit in"
        }
      ]
    },
    {
      "expr_id": "expr_00059",
      "text": "remix of the track became a dance hit in",
      "label": "relation-bearing expression",
      "justification": "Describes the remix's success in the US.",
      "evidence": [
        {
          "chunk_id": "chunk_0000",
          "chunk_start_char": 1189,
          "chunk_end_char": 1229,
          "doc_start_char": 1189,
          "doc_end_char": 1229,
          "snippet": "dom . It attained Silver certification in France and the United Kingdom , and a remix of the track became a dance hit in the United States ."
        }
      ]
    }
  ]
}