{
  "triples": [
    {
      "triple_id": "triple_00000",
      "subject": {
        "id": "cand_r_00000",
        "label": "Lycoming County",
        "type": "relation"
      },
      "predicate": {
        "id": "cand_r_00000",
        "label": "Lycoming County"
      },
      "object": {
        "id": "cand_e_00001",
        "label": "north-central Pennsylvania",
        "type": "entity"
      },
      "chunk_id": "chunk_0000",
      "justification": "The text states that Lycoming County is in north-central Pennsylvania.",
      "confidence": 0.95
    }
  ]
}