{
  "layer": "layer09_general_axiom_extraction",
  "num_general_axiom_candidates": 5,
  "general_axiom_candidates": [
    {
      "axiom_id": "axiom_00000",
      "axiom_type": "relation_domain",
      "subject_id": "ont_rel_00000",
      "subject_label": "dual player",
      "predicate": "domain",
      "object_id": "domain_hint::athlete",
      "object_label": "athlete",
      "literal_value": null,
      "justification": "The relation \"dual player\" links a sportsperson to each sport they compete in, indicating multi‑sport participation.",
      "confidence": 0.95,
      "source_schema_ids": [
        "schema_00000"
      ],
      "source_concept_ids": [],
      "source_relation_ids": [
        "ont_rel_00000"
      ],
      "evidence": [
        {
          "chunk_id": "chunk_0000",
          "chunk_start_char": 609,
          "chunk_end_char": 620,
          "doc_start_char": 609,
          "doc_end_char": 620,
          "snippet": "up on one occasion . At club level Mc Evoy won several championship medals as a dual player with Abbeyleix . He also won a championship medal with the Thomas Davis club ."
        }
      ]
    },
    {
      "axiom_id": "axiom_00001",
      "axiom_type": "relation_range",
      "subject_id": "ont_rel_00000",
      "subject_label": "dual player",
      "predicate": "range",
      "object_id": "range_hint::sport",
      "object_label": "sport",
      "literal_value": null,
      "justification": "The relation \"dual player\" links a sportsperson to each sport they compete in, indicating multi‑sport participation.",
      "confidence": 0.92,
      "source_schema_ids": [
        "schema_00001"
      ],
      "source_concept_ids": [],
      "source_relation_ids": [
        "ont_rel_00000"
      ],
      "evidence": [
        {
          "chunk_id": "chunk_0000",
          "chunk_start_char": 609,
          "chunk_end_char": 620,
          "doc_start_char": 609,
          "doc_end_char": 620,
          "snippet": "up on one occasion . At club level Mc Evoy won several championship medals as a dual player with Abbeyleix . He also won a championship medal with the Thomas Davis club ."
        }
      ]
    },
    {
      "axiom_id": "axiom_00002",
      "axiom_type": "description",
      "subject_id": "concept_00000",
      "subject_label": "town",
      "predicate": "rdfs:description",
      "object_id": null,
      "object_label": null,
      "literal_value": "A human settlement larger than a village but smaller than a city, typically featuring centralized services, infrastructure, and municipal governance.",
      "justification": "Interpretability rule: all ontology entities, concepts, and relations receive rdfs:description.",
      "confidence": 1.0,
      "source_schema_ids": [],
      "source_concept_ids": [
        "concept_00000"
      ],
      "source_relation_ids": [],
      "evidence": [
        {
          "chunk_id": "chunk_0000",
          "chunk_start_char": 119,
          "chunk_end_char": 128,
          "doc_start_char": 119,
          "doc_end_char": 128,
          "snippet": "was an Irish hurler who played for the Dublin and Laois senior teams . Born in Abbeyleix , County Laois , Mc Evoy first played competitive hurling and Gaelic football i"
        }
      ]
    },
    {
      "axiom_id": "axiom_00003",
      "axiom_type": "description",
      "subject_id": "concept_00001",
      "subject_label": "WonMedalEvent",
      "predicate": "rdfs:description",
      "object_id": null,
      "object_label": null,
      "literal_value": "An event in which an individual or group receives a medal for a specific achievement, typically in a competitive or ceremonial context.",
      "justification": "Interpretability rule: all ontology entities, concepts, and relations receive rdfs:description.",
      "confidence": 1.0,
      "source_schema_ids": [],
      "source_concept_ids": [
        "concept_00001"
      ],
      "source_relation_ids": [],
      "evidence": [
        {
          "chunk_id": "chunk_0000",
          "chunk_start_char": 442,
          "chunk_end_char": 469,
          "doc_start_char": 442,
          "doc_end_char": 469,
          "snippet": "retuming to Laois . Mc Evoy was a regular member of the starting fifteen , and won one All - Ireland medal and two Leinster medals . He was an All - Ireland runner - up on one occasion ."
        }
      ]
    },
    {
      "axiom_id": "axiom_00004",
      "axiom_type": "description",
      "subject_id": "ont_rel_00000",
      "subject_label": "dual player",
      "predicate": "rdfs:description",
      "object_id": null,
      "object_label": null,
      "literal_value": "Relates a sportsperson to the sports they compete in, indicating that the individual plays multiple sports.",
      "justification": "Interpretability rule: all ontology entities, concepts, and relations receive rdfs:description.",
      "confidence": 1.0,
      "source_schema_ids": [],
      "source_concept_ids": [],
      "source_relation_ids": [
        "ont_rel_00000"
      ],
      "evidence": [
        {
          "chunk_id": "chunk_0000",
          "chunk_start_char": 609,
          "chunk_end_char": 620,
          "doc_start_char": 609,
          "doc_end_char": 620,
          "snippet": "up on one occasion . At club level Mc Evoy won several championship medals as a dual player with Abbeyleix . He also won a championship medal with the Thomas Davis club ."
        }
      ]
    }
  ]
}