{
  "layer": "layer00_preprocessing",
  "doc_id": "DocRED - 4b0f3668fd6ec489",
  "source_path": "../../../ragtree/data/preprocessed/docred_causal.jsonl",
  "pdf_type": null,
  "content_blocks": [],
  "tables": [],
  "num_chunks": 1,
  "chunks": [
    {
      "chunk_id": "chunk_0000",
      "start_char": 0,
      "end_char": 771,
      "text_preview": "The Beibu Gulf Economic Rim or Beibu Economic Belt ( ) also known as Gulf of Tonkin Economic Belt in ( Vietnamese : Vành đai kinh tế vịnh Bắc Bộ ) defines the economic region or rim surrounding around China 's southwestern coastal region and cities around the Gulf of Tonkin . The region is part of C"
    }
  ]
}